proto2obj/Main.py
proto2obj/__init__.py
proto2obj-1.0.2.dist-info/METADATA
proto2obj-1.0.2.dist-info/WHEEL
proto2obj-1.0.2.dist-info/entry_points.txt
proto2obj-1.0.2.dist-info/top_level.txt
proto2obj-1.0.2.dist-info/RECORD
