Metadata-Version: 2.1
Name: proto2obj
Version: 1.0.2
Summary: Python Package made by Mhadhbi Issam . 
Home-page: https://gitlab.com/game-dev-comapny/libraries/proto2obj.git
Author: mhadhbixissam
Author-email: mhadhbixissam@gmail.com
Project-URL: Documentation, https://pydefold.readthedocs.io/en/latest/
Classifier: Programming Language :: Python :: 3
Classifier: License :: OSI Approved :: MIT License
Classifier: Operating System :: OS Independent
Requires-Dist: protobuf==4.25.0
